odoo/addons/delivery_cbl/README.rst
odoo/addons/delivery_cbl/__init__.py
odoo/addons/delivery_cbl/__manifest__.py
odoo/addons/delivery_cbl/data/ir_cron.xml
odoo/addons/delivery_cbl/i18n/ca.po
odoo/addons/delivery_cbl/i18n/delivery_cbl.pot
odoo/addons/delivery_cbl/i18n/es.po
odoo/addons/delivery_cbl/i18n/it.po
odoo/addons/delivery_cbl/migrations/17.0.1.1.0/post-migration.py
odoo/addons/delivery_cbl/models/__init__.py
odoo/addons/delivery_cbl/models/cbl_request.py
odoo/addons/delivery_cbl/models/delivery_carrier.py
odoo/addons/delivery_cbl/models/stock_picking.py
odoo/addons/delivery_cbl/readme/CONFIGURE.md
odoo/addons/delivery_cbl/readme/CONTRIBUTORS.md
odoo/addons/delivery_cbl/readme/DESCRIPTION.md
odoo/addons/delivery_cbl/readme/ROADMAP.md
odoo/addons/delivery_cbl/readme/USAGE.md
odoo/addons/delivery_cbl/report/cbl_manifest.xml
odoo/addons/delivery_cbl/security/ir.model.access.csv
odoo/addons/delivery_cbl/static/description/icon.png
odoo/addons/delivery_cbl/static/description/index.html
odoo/addons/delivery_cbl/tests/__init__.py
odoo/addons/delivery_cbl/tests/test_delivery_cbl.py
odoo/addons/delivery_cbl/views/delivery_carrier_view.xml
odoo/addons/delivery_cbl/views/stock_picking_views.xml
odoo/addons/delivery_cbl/wizard/__init__.py
odoo/addons/delivery_cbl/wizard/manifest_wizard.py
odoo/addons/delivery_cbl/wizard/wizard_confirm_cbl_pickings.py
odoo/addons/delivery_cbl/wizard/wizard_confirm_cbl_pickings_view.xml
odoo_addon_delivery_cbl-17.0.2.0.0.dist-info/METADATA
odoo_addon_delivery_cbl-17.0.2.0.0.dist-info/WHEEL
odoo_addon_delivery_cbl-17.0.2.0.0.dist-info/top_level.txt
odoo_addon_delivery_cbl-17.0.2.0.0.dist-info/RECORD
