Metadata-Version: 2.1
Name: odoo-addon-delivery_cbl
Version: 17.0.2.0.0
Requires-Python: >=3.10
Requires-Dist: odoo-addon-base_delivery_carrier_label>=17.0dev,<17.1dev
Requires-Dist: odoo-addon-delivery_package_number>=17.0dev,<17.1dev
Requires-Dist: odoo>=17.0a,<17.1dev
Summary: Integrate CBL webservice
Home-page: https://github.com/OCA/delivery-carrier
License: AGPL-3
Author: Sygel, Odoo Community Association (OCA)
Author-email: support@odoo-community.org
Classifier: Programming Language :: Python
Classifier: Framework :: Odoo
Classifier: Framework :: Odoo :: 17.0
Classifier: License :: OSI Approved :: GNU Affero General Public License v3
